RsCMPX_WcdmaMeas/RsCMPX_WcdmaMeas.py
RsCMPX_WcdmaMeas/__init__.py
RsCMPX_WcdmaMeas/enums.py
RsCMPX_WcdmaMeas/repcap.py
RsCMPX_WcdmaMeas/CustomFiles/__init__.py
RsCMPX_WcdmaMeas/CustomFiles/events.py
RsCMPX_WcdmaMeas/CustomFiles/reliability.py
RsCMPX_WcdmaMeas/CustomFiles/utilities.py
RsCMPX_WcdmaMeas/Implementations/__init__.py
RsCMPX_WcdmaMeas/Implementations/Configure/__init__.py
RsCMPX_WcdmaMeas/Implementations/Configure/WcdmaMeas/OlpControl.py
RsCMPX_WcdmaMeas/Implementations/Configure/WcdmaMeas/__init__.py
RsCMPX_WcdmaMeas/Implementations/Configure/WcdmaMeas/Carrier/Band.py
RsCMPX_WcdmaMeas/Implementations/Configure/WcdmaMeas/Carrier/__init__.py
RsCMPX_WcdmaMeas/Implementations/Configure/WcdmaMeas/Cell/__init__.py
RsCMPX_WcdmaMeas/Implementations/Configure/WcdmaMeas/Cell/Carrier/Scode.py
RsCMPX_WcdmaMeas/Implementations/Configure/WcdmaMeas/Cell/Carrier/__init__.py
RsCMPX_WcdmaMeas/Implementations/Configure/WcdmaMeas/MultiEval/Amode.py
RsCMPX_WcdmaMeas/Implementations/Configure/WcdmaMeas/MultiEval/CdThreshold.py
RsCMPX_WcdmaMeas/Implementations/Configure/WcdmaMeas/MultiEval/Dmode.py
RsCMPX_WcdmaMeas/Implementations/Configure/WcdmaMeas/MultiEval/DsFactor.py
RsCMPX_WcdmaMeas/Implementations/Configure/WcdmaMeas/MultiEval/Mperiod.py
RsCMPX_WcdmaMeas/Implementations/Configure/WcdmaMeas/MultiEval/Rotation.py
RsCMPX_WcdmaMeas/Implementations/Configure/WcdmaMeas/MultiEval/Scount.py
RsCMPX_WcdmaMeas/Implementations/Configure/WcdmaMeas/MultiEval/Sscalar.py
RsCMPX_WcdmaMeas/Implementations/Configure/WcdmaMeas/MultiEval/__init__.py
RsCMPX_WcdmaMeas/Implementations/Configure/WcdmaMeas/MultiEval/Limit/EvMagnitude.py
RsCMPX_WcdmaMeas/Implementations/Configure/WcdmaMeas/MultiEval/Limit/Merror.py
RsCMPX_WcdmaMeas/Implementations/Configure/WcdmaMeas/MultiEval/Limit/Perror.py
RsCMPX_WcdmaMeas/Implementations/Configure/WcdmaMeas/MultiEval/Limit/Phd.py
RsCMPX_WcdmaMeas/Implementations/Configure/WcdmaMeas/MultiEval/Limit/PhsDpcch.py
RsCMPX_WcdmaMeas-5.0.40.dist-info/METADATA
RsCMPX_WcdmaMeas-5.0.40.dist-info/WHEEL
RsCMPX_WcdmaMeas-5.0.40.dist-info/top_level.txt
RsCMPX_WcdmaMeas-5.0.40.dist-info/RECORD
